require_api_key.py
flask_api_key_decorator-0.1.3.dist-info/LICENSE.md
flask_api_key_decorator-0.1.3.dist-info/METADATA
flask_api_key_decorator-0.1.3.dist-info/WHEEL
flask_api_key_decorator-0.1.3.dist-info/top_level.txt
flask_api_key_decorator-0.1.3.dist-info/RECORD
