Metadata-Version: 2.1
Name: flask-api-key-decorator
Version: 0.1.3
Summary: Simple Flask decorator for requiring an API key
Author-email: "@lumpenspace" <lumpenspace@gmail.com>
License: Copyright 2023 @lumpenspace
Project-URL: homepage, https://github.com/yourusername/flask-api-key-decorator
Project-URL: repository, https://github.com/yourusername/flask-api-key-decorator
Project-URL: documentation, https://yourusername.github.io/flask-api-key-decorator
License-File: LICENSE.md
Requires-Dist: flask
